stemma/__init__.py
stemma-0.0.1.dist-info/METADATA
stemma-0.0.1.dist-info/WHEEL
stemma-0.0.1.dist-info/top_level.txt
stemma-0.0.1.dist-info/RECORD
