Metadata-Version: 2.1
Name: stemma
Version: 0.0.1
Summary: The Stemma Python Client
Home-page: UNKNOWN
Author: Stemma
Author-email: developers@stemma.ai
License: UNKNOWN
Platform: UNKNOWN
